package/__init__.py
bullworkpackage-0.0.2.dist-info/METADATA
bullworkpackage-0.0.2.dist-info/WHEEL
bullworkpackage-0.0.2.dist-info/top_level.txt
bullworkpackage-0.0.2.dist-info/RECORD
