Metadata-Version: 2.1
Name: bullworkpackage
Version: 0.0.2
Summary: abc
Home-page: https://github.com/sandesh-bullwork/package
Author: SN
